tf_seq2seq_losses/__init__.py
tf_seq2seq_losses/base_loss.py
tf_seq2seq_losses/classic_ctc_loss.py
tf_seq2seq_losses/simplified_ctc_loss.py
tf_seq2seq_losses/tools.py
tf_seq2seq_losses-0.3.0.dist-info/LICENSE
tf_seq2seq_losses-0.3.0.dist-info/METADATA
tf_seq2seq_losses-0.3.0.dist-info/WHEEL
tf_seq2seq_losses-0.3.0.dist-info/top_level.txt
tf_seq2seq_losses-0.3.0.dist-info/RECORD
