Metadata-Version: 2.1
Name: tf-seq2seq-losses
Version: 0.3.0
Summary: Tensorflow implementations for (CTC) loss functions that are fast and support second-order derivatives.
Home-page: https://github.com/alexeytochin/tf-seq2seq-losses
Author: Alexey Tochin
Author-email: alexey.tochin@gmail.com
License: Apache 2.0
Project-URL: Documentation, https://github.com/alexeytochin/tf-seq2seq-losses/README.md
Project-URL: GitHub, https://github.com/alexeytochin/tf-seq2seq-losses
Project-URL: Changelog, https://github.com/alexeytochin/tf-seq2seq-losses/CHANGELOG.md
Keywords: tensorflow,loss,loss function,ctc,connectionist temporal classification,seq2se,seq 2 seq,seq to seq,asr,automatic speach recognition,sequence recognitionhessian,second derivative
Classifier: Development Status :: 4 - Beta
Classifier: Intended Audience :: Science/Research
Classifier: Intended Audience :: Developers
Classifier: License :: OSI Approved :: Apache Software License
Classifier: Operating System :: POSIX :: Linux
Classifier: Programming Language :: Python :: 3.7
Classifier: Programming Language :: Python :: 3.8
Classifier: Programming Language :: Python :: 3.9
Classifier: Programming Language :: Python :: 3.10
Classifier: Programming Language :: Python :: 3.11
License-File: LICENSE
Requires-Dist: tensorflow >=2.6.1
Requires-Dist: numpy
